aioduckdb/__init__.py
aioduckdb/__version__.py
aioduckdb/context.py
aioduckdb/core.py
aioduckdb/cursor.py
aioduckdb/py.typed
aioduckdb/relation.py
aioduckdb/result.py
aioduckdb/tests/__init__.py
aioduckdb/tests/__main__.py
aioduckdb/tests/arrow.py
aioduckdb/tests/helpers.py
aioduckdb/tests/perf.py
aioduckdb/tests/relations.py
aioduckdb/tests/smoke.py
aioduckdb/tests/test_parquet.py
aioduckdb/tests/data/binary_string.parquet
aioduckdb/tests/data/userdata1.parquet
aioduckdb-0.1.0.dist-info/LICENSE
aioduckdb-0.1.0.dist-info/WHEEL
aioduckdb-0.1.0.dist-info/METADATA
aioduckdb-0.1.0.dist-info/RECORD
