Metadata-Version: 2.1
Name: aioduckdb
Version: 0.1.0
Summary: asyncio bridge to the standard sqlite3 module
Home-page: https://github.com/kouta-kun/aioduckdb
Author: Salvador Pardiñas
Author-email: darkfm@vera.com.uy
Requires-Python: >=3.6
Classifier: Development Status :: 5 - Production/Stable
Classifier: Framework :: AsyncIO
Classifier: Intended Audience :: Developers
Classifier: License :: OSI Approved :: MIT License
Classifier: Topic :: Software Development :: Libraries
Requires-Dist: duckdb
Requires-Dist: typing_extensions >= 4.0; python_version < '3.8'
Project-URL: Github, https://github.com/kouta-kun/aioduckdb
